{
    "000": {
        "000": "17 BAS_DASH_F",
        "001": "18 BAS_DASH_B",
        "003": "600 ATK_5LP",
        "004": "609 ATK_5LK",
        "005": "604 ATK_5MP",
        "006": "612 ATK_5MK",
        "007": "606 ATK_5HP",
        "008": "615 ATK_5HK",
        "010": "618 ATK_2LP",
        "011": "628 ATK_2LK",
        "012": "622 ATK_2MP",
        "013": "632 ATK_2MK",
        "014": "625 ATK_2HP",
        "015": "635 ATK_2HK",
        "025": "648 ATK_4HK",
        "026": "647 ATK_4MP",
        "027": "649 ATK_6HK",
        "064": "945 SPA_FC_LOOP",
        "065": "946 SPA_FC_LOOP(1)",
        "066": "947 SPA_FC_LOOP(2)",
        "069": "935 SPA_ACSELSPINKNUCKLE_H",
        "070": "936 SPA_ACSELSPINKNUCKLE_H(1)",
        "071": "937 SPA_ACSELSPINKNUCKLE_H(2)",
        "074": "900 SPA_SPIRALARROW_END",
        "075": "902 SPA_SPIRALARROW_END(1)",
        "076": "904 SPA_SPIRALARROW_END(2)",
        "079": "915 SPA_CANNONSPIKE_AIR",
        "080": "916 SPA_CANNONSPIKE_AIR(1)",
        "081": "919 SPA_CANNONSPIKE_AIR(4)",
        "100": "900 SPA_SPIRALARROW_END",
        "101": "902 SPA_SPIRALARROW_END(1)",
        "102": "904 SPA_SPIRALARROW_END(2)",
        "117": "480 DPA_STD_START",
        "124": "715 NGS",
        "134": "855 ATK_CTA",
        "146": "1200 SPA_SPIRALARROW_END(5)",
        "148": "1210 SA2_KILLERBEESPIN_START",
        "156": "1231 SPA_SPIRALARROW_END(6)",
        "160": "1241 SPA_SPIRALARROW_END(7)",
        "174": "949 SPA_FC_LOOP(4)",
        "175": "950 SPA_FC_LOOP(5)",
        "176": "951 SPA_FC_LOOP(6)",
        "177": "938 SPA_ACSELSPINKNUCKLE_H(3)",
        "179": "910 SPA_SPIRALARROW_END(4)",
        "180": "923 SPA_CANNONSPIKE_AIR(6)",
        "186": "910 SPA_SPIRALARROW_END(4)",
        "207": "1500 DEM_APPEAL_01(2)",
        "215": "1100 _1100",
        "219": "1104 _1104",
        "222": "1116 _1116"
    },
    "001": {
        "017": "638 ATK_8LP",
        "018": "641 ATK_8LK",
        "019": "639 ATK_8MP",
        "020": "642 ATK_8MK",
        "021": "640 ATK_8HP",
        "022": "643 ATK_8HK",
        "127": "730 NGS_AIR",
        "128": "730 NGS_AIR",
        "129": "730 NGS_AIR"
    },
    "002": {
        "017": "638 ATK_8LP",
        "018": "641 ATK_8LK",
        "019": "639 ATK_8MP",
        "020": "642 ATK_8MK",
        "021": "640 ATK_8HP",
        "022": "643 ATK_8HK",
        "127": "730 NGS_AIR",
        "128": "730 NGS_AIR",
        "129": "730 NGS_AIR"
    },
    "003": {
        "064": "945 SPA_FC_LOOP",
        "065": "946 SPA_FC_LOOP(1)",
        "066": "947 SPA_FC_LOOP(2)",
        "069": "935 SPA_ACSELSPINKNUCKLE_H",
        "070": "936 SPA_ACSELSPINKNUCKLE_H(1)",
        "071": "937 SPA_ACSELSPINKNUCKLE_H(2)",
        "074": "900 SPA_SPIRALARROW_END",
        "075": "902 SPA_SPIRALARROW_END(1)",
        "076": "904 SPA_SPIRALARROW_END(2)",
        "079": "915 SPA_CANNONSPIKE_AIR",
        "080": "916 SPA_CANNONSPIKE_AIR(1)",
        "081": "919 SPA_CANNONSPIKE_AIR(4)",
        "100": "900 SPA_SPIRALARROW_END",
        "101": "902 SPA_SPIRALARROW_END(1)",
        "102": "904 SPA_SPIRALARROW_END(2)",
        "117": "480 DPA_STD_START",
        "134": "855 ATK_CTA",
        "146": "1200 SPA_SPIRALARROW_END(5)",
        "148": "1210 SA2_KILLERBEESPIN_START",
        "156": "1231 SPA_SPIRALARROW_END(6)",
        "160": "1241 SPA_SPIRALARROW_END(7)",
        "174": "949 SPA_FC_LOOP(4)",
        "175": "950 SPA_FC_LOOP(5)",
        "176": "951 SPA_FC_LOOP(6)",
        "177": "938 SPA_ACSELSPINKNUCKLE_H(3)",
        "179": "910 SPA_SPIRALARROW_END(4)",
        "180": "923 SPA_CANNONSPIKE_AIR(6)",
        "186": "910 SPA_SPIRALARROW_END(4)"
    },
    "004": {
        "064": "945 SPA_FC_LOOP",
        "065": "946 SPA_FC_LOOP(1)",
        "066": "947 SPA_FC_LOOP(2)",
        "069": "935 SPA_ACSELSPINKNUCKLE_H",
        "070": "936 SPA_ACSELSPINKNUCKLE_H(1)",
        "071": "937 SPA_ACSELSPINKNUCKLE_H(2)",
        "074": "900 SPA_SPIRALARROW_END",
        "075": "902 SPA_SPIRALARROW_END(1)",
        "076": "904 SPA_SPIRALARROW_END(2)",
        "079": "915 SPA_CANNONSPIKE_AIR",
        "080": "916 SPA_CANNONSPIKE_AIR(1)",
        "081": "919 SPA_CANNONSPIKE_AIR(4)",
        "100": "900 SPA_SPIRALARROW_END",
        "101": "902 SPA_SPIRALARROW_END(1)",
        "102": "904 SPA_SPIRALARROW_END(2)",
        "146": "1200 SPA_SPIRALARROW_END(5)",
        "148": "1210 SA2_KILLERBEESPIN_START",
        "156": "1231 SPA_SPIRALARROW_END(6)",
        "160": "1241 SPA_SPIRALARROW_END(7)",
        "174": "949 SPA_FC_LOOP(4)",
        "175": "950 SPA_FC_LOOP(5)",
        "176": "951 SPA_FC_LOOP(6)",
        "177": "938 SPA_ACSELSPINKNUCKLE_H(3)",
        "179": "910 SPA_SPIRALARROW_END(4)",
        "180": "923 SPA_CANNONSPIKE_AIR(6)",
        "186": "910 SPA_SPIRALARROW_END(4)"
    },
    "005": {
        "001": "18 BAS_DASH_B",
        "064": "945 SPA_FC_LOOP",
        "065": "946 SPA_FC_LOOP(1)",
        "066": "947 SPA_FC_LOOP(2)",
        "069": "935 SPA_ACSELSPINKNUCKLE_H",
        "070": "936 SPA_ACSELSPINKNUCKLE_H(1)",
        "071": "937 SPA_ACSELSPINKNUCKLE_H(2)",
        "074": "900 SPA_SPIRALARROW_END",
        "075": "902 SPA_SPIRALARROW_END(1)",
        "076": "904 SPA_SPIRALARROW_END(2)",
        "079": "915 SPA_CANNONSPIKE_AIR",
        "080": "916 SPA_CANNONSPIKE_AIR(1)",
        "081": "919 SPA_CANNONSPIKE_AIR(4)",
        "100": "900 SPA_SPIRALARROW_END",
        "101": "902 SPA_SPIRALARROW_END(1)",
        "102": "904 SPA_SPIRALARROW_END(2)",
        "117": "480 DPA_STD_START",
        "134": "855 ATK_CTA",
        "146": "1200 SPA_SPIRALARROW_END(5)",
        "148": "1210 SA2_KILLERBEESPIN_START",
        "151": "1211 SA2_KILLERBEESPIN_START(1)",
        "153": "1211 SA2_KILLERBEESPIN_START(1)",
        "156": "1231 SPA_SPIRALARROW_END(6)",
        "158": "1231 SPA_SPIRALARROW_END(6)",
        "160": "1241 SPA_SPIRALARROW_END(7)",
        "162": "1241 SPA_SPIRALARROW_END(7)",
        "174": "949 SPA_FC_LOOP(4)",
        "175": "950 SPA_FC_LOOP(5)",
        "176": "951 SPA_FC_LOOP(6)",
        "177": "938 SPA_ACSELSPINKNUCKLE_H(3)",
        "179": "910 SPA_SPIRALARROW_END(4)",
        "180": "923 SPA_CANNONSPIKE_AIR(6)",
        "186": "910 SPA_SPIRALARROW_END(4)"
    },
    "010": {
        "118": "500 ATK_CTA_RUSH",
        "119": "500 ATK_CTA_RUSH"
    },
    "011": {
        "135": "850 ATK_CTA_4_Y2"
    },
    "012": {
        "057": "501 ATK_CTA_RUSH(1)",
        "121": "501 ATK_CTA_RUSH(1)"
    },
    "015": {
        "064": "945 SPA_FC_LOOP",
        "065": "946 SPA_FC_LOOP(1)",
        "066": "947 SPA_FC_LOOP(2)",
        "069": "935 SPA_ACSELSPINKNUCKLE_H",
        "070": "936 SPA_ACSELSPINKNUCKLE_H(1)",
        "071": "937 SPA_ACSELSPINKNUCKLE_H(2)",
        "074": "900 SPA_SPIRALARROW_END",
        "075": "902 SPA_SPIRALARROW_END(1)",
        "076": "904 SPA_SPIRALARROW_END(2)",
        "079": "915 SPA_CANNONSPIKE_AIR",
        "080": "916 SPA_CANNONSPIKE_AIR(1)",
        "081": "919 SPA_CANNONSPIKE_AIR(4)",
        "100": "900 SPA_SPIRALARROW_END",
        "101": "902 SPA_SPIRALARROW_END(1)",
        "102": "904 SPA_SPIRALARROW_END(2)",
        "117": "480 DPA_STD_START",
        "124": "715 NGS",
        "134": "855 ATK_CTA",
        "146": "1200 SPA_SPIRALARROW_END(5)",
        "148": "1210 SA2_KILLERBEESPIN_START",
        "156": "1231 SPA_SPIRALARROW_END(6)",
        "160": "1241 SPA_SPIRALARROW_END(7)",
        "174": "949 SPA_FC_LOOP(4)",
        "175": "950 SPA_FC_LOOP(5)",
        "176": "951 SPA_FC_LOOP(6)",
        "177": "938 SPA_ACSELSPINKNUCKLE_H(3)",
        "179": "910 SPA_SPIRALARROW_END(4)",
        "180": "923 SPA_CANNONSPIKE_AIR(6)",
        "186": "910 SPA_SPIRALARROW_END(4)",
        "207": "1500 DEM_APPEAL_01(2)"
    },
    "017": {
        "146": "1200 SPA_SPIRALARROW_END(5)",
        "148": "1210 SA2_KILLERBEESPIN_START",
        "156": "1231 SPA_SPIRALARROW_END(6)",
        "160": "1241 SPA_SPIRALARROW_END(7)",
        "174": "949 SPA_FC_LOOP(4)",
        "175": "950 SPA_FC_LOOP(5)",
        "176": "951 SPA_FC_LOOP(6)",
        "177": "938 SPA_ACSELSPINKNUCKLE_H(3)",
        "179": "910 SPA_SPIRALARROW_END(4)",
        "180": "923 SPA_CANNONSPIKE_AIR(6)",
        "186": "910 SPA_SPIRALARROW_END(4)"
    },
    "019": {
        "127": "730 NGS_AIR",
        "128": "730 NGS_AIR",
        "129": "730 NGS_AIR"
    },
    "021": {
        "151": "1211 SA2_KILLERBEESPIN_START(1)",
        "153": "1211 SA2_KILLERBEESPIN_START(1)",
        "189": "1016 SPA_CANNONSTRIKE_H_START",
        "191": "1016 SPA_CANNONSTRIKE_H_START"
    },
    "022": {
        "038": "651 ATK_4MP_HK"
    },
    "023": {
        "041": "652 ATK_TC_5HP_5HK"
    },
    "024": {
        "048": "750 BAS_JUMP_F_START(1)"
    },
    "025": {
        "105": "1013 SPA_CANNONSTRIKE_L_AIR(1)",
        "106": "1014 SPA_CANNONSTRIKE_M_AIR(1)",
        "107": "1015 SPA_CANNONSTRIKE_H_AIR",
        "109": "1013 SPA_CANNONSTRIKE_L_AIR(1)",
        "110": "1014 SPA_CANNONSTRIKE_M_AIR(1)",
        "111": "1015 SPA_CANNONSTRIKE_H_AIR",
        "151": "1211 SA2_KILLERBEESPIN_START(1)",
        "189": "1016 SPA_CANNONSTRIKE_H_START",
        "190": "1016 SPA_CANNONSTRIKE_H_START"
    },
    "027": {
        "097": "970 SPA_FC_THROW_MISS"
    },
    "028": {
        "098": "975 SPA_FC_THROW_MISS(1)"
    },
    "029": {
        "185": "979 SPA_FC_THROW_MISS(2)"
    },
    "031": {
        "064": "945 SPA_FC_LOOP",
        "065": "946 SPA_FC_LOOP(1)",
        "066": "947 SPA_FC_LOOP(2)",
        "069": "935 SPA_ACSELSPINKNUCKLE_H",
        "070": "936 SPA_ACSELSPINKNUCKLE_H(1)",
        "071": "937 SPA_ACSELSPINKNUCKLE_H(2)",
        "074": "900 SPA_SPIRALARROW_END",
        "075": "902 SPA_SPIRALARROW_END(1)",
        "076": "904 SPA_SPIRALARROW_END(2)",
        "079": "915 SPA_CANNONSPIKE_AIR",
        "080": "916 SPA_CANNONSPIKE_AIR(1)",
        "081": "919 SPA_CANNONSPIKE_AIR(4)",
        "100": "900 SPA_SPIRALARROW_END",
        "101": "902 SPA_SPIRALARROW_END(1)",
        "102": "904 SPA_SPIRALARROW_END(2)",
        "134": "855 ATK_CTA",
        "146": "1200 SPA_SPIRALARROW_END(5)",
        "148": "1210 SA2_KILLERBEESPIN_START",
        "156": "1231 SPA_SPIRALARROW_END(6)",
        "160": "1241 SPA_SPIRALARROW_END(7)",
        "174": "949 SPA_FC_LOOP(4)",
        "175": "950 SPA_FC_LOOP(5)",
        "176": "951 SPA_FC_LOOP(6)",
        "177": "938 SPA_ACSELSPINKNUCKLE_H(3)",
        "179": "910 SPA_SPIRALARROW_END(4)",
        "180": "923 SPA_CANNONSPIKE_AIR(6)",
        "186": "910 SPA_SPIRALARROW_END(4)"
    },
    "033": {
        "057": "501 ATK_CTA_RUSH(1)",
        "064": "945 SPA_FC_LOOP",
        "065": "946 SPA_FC_LOOP(1)",
        "066": "947 SPA_FC_LOOP(2)",
        "069": "935 SPA_ACSELSPINKNUCKLE_H",
        "070": "936 SPA_ACSELSPINKNUCKLE_H(1)",
        "071": "937 SPA_ACSELSPINKNUCKLE_H(2)",
        "074": "900 SPA_SPIRALARROW_END",
        "075": "902 SPA_SPIRALARROW_END(1)",
        "076": "904 SPA_SPIRALARROW_END(2)",
        "079": "915 SPA_CANNONSPIKE_AIR",
        "080": "916 SPA_CANNONSPIKE_AIR(1)",
        "081": "919 SPA_CANNONSPIKE_AIR(4)",
        "100": "900 SPA_SPIRALARROW_END",
        "101": "902 SPA_SPIRALARROW_END(1)",
        "102": "904 SPA_SPIRALARROW_END(2)",
        "121": "501 ATK_CTA_RUSH(1)",
        "134": "855 ATK_CTA",
        "146": "1200 SPA_SPIRALARROW_END(5)",
        "148": "1210 SA2_KILLERBEESPIN_START",
        "156": "1231 SPA_SPIRALARROW_END(6)",
        "160": "1241 SPA_SPIRALARROW_END(7)",
        "174": "949 SPA_FC_LOOP(4)",
        "175": "950 SPA_FC_LOOP(5)",
        "176": "951 SPA_FC_LOOP(6)",
        "177": "938 SPA_ACSELSPINKNUCKLE_H(3)",
        "179": "910 SPA_SPIRALARROW_END(4)",
        "180": "923 SPA_CANNONSPIKE_AIR(6)",
        "186": "910 SPA_SPIRALARROW_END(4)"
    },
    "036": {
        "148": "1210 SA2_KILLERBEESPIN_START",
        "158": "1231 SPA_SPIRALARROW_END(6)",
        "162": "1241 SPA_SPIRALARROW_END(7)"
    },
    "038": {
        "158": "1231 SPA_SPIRALARROW_END(6)",
        "162": "1241 SPA_SPIRALARROW_END(7)"
    },
    "039": {
        "148": "1210 SA2_KILLERBEESPIN_START",
        "158": "1231 SPA_SPIRALARROW_END(6)",
        "162": "1241 SPA_SPIRALARROW_END(7)"
    },
    "041": {
        "031": "601 ATK_5LP_C",
        "034": "620 ATK_2LP(1)",
        "036": "630 ATK_2LK(1)"
    },
    "042": {
        "032": "602 ATK_5LP(1)",
        "033": "619 ATK_2LP_C",
        "036": "630 ATK_2LK(1)"
    },
    "043": {
        "032": "602 ATK_5LP(1)",
        "034": "620 ATK_2LP(1)",
        "035": "629 ATK_2LK_C"
    },
    "046": {
        "039": "620 ATK_2LP(1)"
    },
    "048": {
        "117": "480 DPA_STD_START"
    },
    "050": {
        "057": "501 ATK_CTA_RUSH(1)",
        "064": "945 SPA_FC_LOOP",
        "065": "946 SPA_FC_LOOP(1)",
        "066": "947 SPA_FC_LOOP(2)",
        "069": "935 SPA_ACSELSPINKNUCKLE_H",
        "070": "936 SPA_ACSELSPINKNUCKLE_H(1)",
        "071": "937 SPA_ACSELSPINKNUCKLE_H(2)",
        "074": "900 SPA_SPIRALARROW_END",
        "075": "902 SPA_SPIRALARROW_END(1)",
        "076": "904 SPA_SPIRALARROW_END(2)",
        "079": "915 SPA_CANNONSPIKE_AIR",
        "080": "916 SPA_CANNONSPIKE_AIR(1)",
        "081": "919 SPA_CANNONSPIKE_AIR(4)",
        "100": "900 SPA_SPIRALARROW_END",
        "101": "902 SPA_SPIRALARROW_END(1)",
        "102": "904 SPA_SPIRALARROW_END(2)",
        "121": "501 ATK_CTA_RUSH(1)",
        "134": "855 ATK_CTA",
        "146": "1200 SPA_SPIRALARROW_END(5)",
        "148": "1210 SA2_KILLERBEESPIN_START",
        "156": "1231 SPA_SPIRALARROW_END(6)",
        "160": "1241 SPA_SPIRALARROW_END(7)",
        "174": "949 SPA_FC_LOOP(4)",
        "175": "950 SPA_FC_LOOP(5)",
        "176": "951 SPA_FC_LOOP(6)",
        "178": "942 SPA_ACSELSPINKNUCKLE_H(6)",
        "179": "910 SPA_SPIRALARROW_END(4)",
        "180": "923 SPA_CANNONSPIKE_AIR(6)",
        "186": "910 SPA_SPIRALARROW_END(4)"
    },
    "055": {
        "153": "1211 SA2_KILLERBEESPIN_START(1)"
    },
    "058": {
        "017": "638 ATK_8LP",
        "018": "641 ATK_8LK",
        "019": "639 ATK_8MP",
        "020": "642 ATK_8MK",
        "021": "640 ATK_8HP",
        "022": "643 ATK_8HK",
        "105": "1013 SPA_CANNONSTRIKE_L_AIR(1)",
        "106": "1014 SPA_CANNONSTRIKE_M_AIR(1)",
        "107": "1015 SPA_CANNONSTRIKE_H_AIR",
        "109": "1013 SPA_CANNONSTRIKE_L_AIR(1)",
        "110": "1014 SPA_CANNONSTRIKE_M_AIR(1)",
        "111": "1015 SPA_CANNONSTRIKE_H_AIR",
        "127": "730 NGS_AIR",
        "128": "730 NGS_AIR",
        "129": "730 NGS_AIR",
        "151": "1211 SA2_KILLERBEESPIN_START(1)",
        "189": "1016 SPA_CANNONSTRIKE_H_START",
        "190": "1016 SPA_CANNONSTRIKE_H_START"
    },
    "060": {
        "136": "852 ATK_CTA_4_Y2(2)"
    },
    "061": {
        "113": "1013 SPA_CANNONSTRIKE_L_AIR(1)",
        "114": "1014 SPA_CANNONSTRIKE_M_AIR(1)",
        "115": "1015 SPA_CANNONSTRIKE_H_AIR",
        "153": "1211 SA2_KILLERBEESPIN_START(1)",
        "191": "1016 SPA_CANNONSTRIKE_H_START"
    },
    "062": {
        "105": "1013 SPA_CANNONSTRIKE_L_AIR(1)",
        "106": "1014 SPA_CANNONSTRIKE_M_AIR(1)",
        "107": "1015 SPA_CANNONSTRIKE_H_AIR",
        "109": "1013 SPA_CANNONSTRIKE_L_AIR(1)",
        "110": "1014 SPA_CANNONSTRIKE_M_AIR(1)",
        "111": "1015 SPA_CANNONSTRIKE_H_AIR",
        "151": "1211 SA2_KILLERBEESPIN_START(1)",
        "189": "1016 SPA_CANNONSTRIKE_H_START",
        "190": "1016 SPA_CANNONSTRIKE_H_START"
    },
    "063": {
        "085": "964 SPA_S_STEP",
        "089": "1005 SPA_CANNONSTRIKE_L_AIR",
        "090": "1006 SPA_CANNONSTRIKE_M_AIR",
        "091": "1007 SPA_CANNONSTRIKE_AIR",
        "093": "999 SPA_REVEDGE(1)",
        "094": "985 SPA_REVEDGE",
        "097": "970 SPA_FC_THROW_MISS"
    },
    "064": {
        "086": "965 SPA_S_STEP(1)",
        "092": "1008 SPA_CANNONSTRIKE",
        "095": "1001 SPA_REVEDGE_EX(3)",
        "096": "987 SPA_REVEDGE_EX",
        "098": "975 SPA_FC_THROW_MISS(1)"
    },
    "065": {
        "181": "966 SPA_S_STEP(2)",
        "182": "1009 SPA_CANNONSTRIKE(1)",
        "183": "1000 SPA_REVEDGE_EX(2)",
        "184": "989 SPA_REVEDGE_EX(1)",
        "185": "979 SPA_FC_THROW_MISS(2)"
    },
    "067": {
        "105": "1013 SPA_CANNONSTRIKE_L_AIR(1)",
        "106": "1014 SPA_CANNONSTRIKE_M_AIR(1)",
        "107": "1015 SPA_CANNONSTRIKE_H_AIR",
        "109": "1013 SPA_CANNONSTRIKE_L_AIR(1)",
        "110": "1014 SPA_CANNONSTRIKE_M_AIR(1)",
        "111": "1015 SPA_CANNONSTRIKE_H_AIR",
        "151": "1211 SA2_KILLERBEESPIN_START(1)",
        "189": "1016 SPA_CANNONSTRIKE_H_START",
        "190": "1016 SPA_CANNONSTRIKE_H_START"
    },
    "123": {
        "003": "600 ATK_5LP",
        "004": "609 ATK_5LK",
        "005": "604 ATK_5MP",
        "006": "612 ATK_5MK",
        "007": "606 ATK_5HP",
        "008": "615 ATK_5HK",
        "010": "618 ATK_2LP",
        "011": "628 ATK_2LK",
        "012": "622 ATK_2MP",
        "013": "632 ATK_2MK",
        "014": "625 ATK_2HP",
        "015": "635 ATK_2HK",
        "025": "648 ATK_4HK",
        "026": "647 ATK_4MP",
        "027": "649 ATK_6HK",
        "064": "945 SPA_FC_LOOP",
        "065": "946 SPA_FC_LOOP(1)",
        "066": "947 SPA_FC_LOOP(2)",
        "069": "935 SPA_ACSELSPINKNUCKLE_H",
        "070": "936 SPA_ACSELSPINKNUCKLE_H(1)",
        "071": "937 SPA_ACSELSPINKNUCKLE_H(2)",
        "074": "900 SPA_SPIRALARROW_END",
        "075": "902 SPA_SPIRALARROW_END(1)",
        "076": "904 SPA_SPIRALARROW_END(2)",
        "079": "915 SPA_CANNONSPIKE_AIR",
        "080": "916 SPA_CANNONSPIKE_AIR(1)",
        "081": "919 SPA_CANNONSPIKE_AIR(4)",
        "100": "900 SPA_SPIRALARROW_END",
        "101": "902 SPA_SPIRALARROW_END(1)",
        "102": "904 SPA_SPIRALARROW_END(2)",
        "124": "715 NGS",
        "134": "855 ATK_CTA",
        "146": "1200 SPA_SPIRALARROW_END(5)",
        "148": "1210 SA2_KILLERBEESPIN_START",
        "156": "1231 SPA_SPIRALARROW_END(6)",
        "160": "1241 SPA_SPIRALARROW_END(7)",
        "174": "949 SPA_FC_LOOP(4)",
        "175": "950 SPA_FC_LOOP(5)",
        "176": "951 SPA_FC_LOOP(6)",
        "177": "938 SPA_ACSELSPINKNUCKLE_H(3)",
        "179": "910 SPA_SPIRALARROW_END(4)",
        "180": "923 SPA_CANNONSPIKE_AIR(6)",
        "186": "910 SPA_SPIRALARROW_END(4)"
    }
}